8bitProcessor/alu8.v
// ============================================================
// alu8.v -- 8-bit Arithmetic/Logic Unit (combinational)
// ============================================================
`timescale 1ns/1ps

module alu8 (
    input  wire [7:0] a,
    input  wire [7:0] b,
    input  wire [3:0] op,
    output reg  [7:0] result,
    output wire       zero,      // result == 0
    output reg        carry      // carry-out / borrow / shift-out bit
);

    // ALU operation codes
    localparam ALU_ADD = 4'h0;
    localparam ALU_SUB = 4'h1;
    localparam ALU_AND = 4'h2;
    localparam ALU_OR  = 4'h3;
    localparam ALU_XOR = 4'h4;
    localparam ALU_NOT = 4'h5;  // result = ~a
    localparam ALU_SHL = 4'h6;  // result = a << 1
    localparam ALU_SHR = 4'h7;  // result = a >> 1
    localparam ALU_PASS_A = 4'h8; // result = a (used for LDA/LDI/IN/MOVBA)
    localparam ALU_INC = 4'h9;  // result = a + 1
    localparam ALU_DEC = 4'hA;  // result = a - 1

    reg [8:0] wide; // 9-bit for carry/borrow detection

    always @(*) begin
        wide   = 9'd0;
        carry  = 1'b0;
        result = 8'h00;
        case (op)
            ALU_ADD: begin
                wide   = {1'b0, a} + {1'b0, b};
                result = wide[7:0];
                carry  = wide[8];
            end
            ALU_SUB: begin
                wide   = {1'b0, a} - {1'b0, b};
                result = wide[7:0];
                carry  = wide[8]; // 1 = borrow occurred
            end
            ALU_AND: result = a & b;
            ALU_OR : result = a | b;
            ALU_XOR: result = a ^ b;
            ALU_NOT: result = ~a;
            ALU_SHL: begin
                result = {a[6:0], 1'b0};
                carry  = a[7];
            end
            ALU_SHR: begin
                result = {1'b0, a[7:1]};
                carry  = a[0];
            end
            ALU_PASS_A: result = a;
            ALU_INC: begin
                wide   = {1'b0, a} + 9'd1;
                result = wide[7:0];
                carry  = wide[8];
            end
            ALU_DEC: begin
                wide   = {1'b0, a} - 9'd1;
                result = wide[7:0];
                carry  = wide[8];
            end
            default: result = 8'h00;
        endcase
    end

    assign zero = (result == 8'h00);

endmodule

8bitProcessor/memory8.v
// ============================================================
// memory8.v -- 256 x 8-bit unified program/data memory
//   - Combinational read (address -> data, same cycle)
//   - Synchronous write on rising clk edge when we=1
//   - Preloaded from a hex file via $readmemh (for simulation /
//     FPGA block-RAM initial-value inference)
// ============================================================
`timescale 1ns/1ps

module memory8 #(
    parameter MEM_INIT_FILE = ""
) (
    input  wire       clk,
    input  wire [7:0] addr,
    input  wire [7:0] wdata,
    input  wire       we,
    output wire [7:0] rdata
);

    reg [7:0] mem [0:255];

    // Runtime program selection: `vvp sim.out +HEXFILE=sw/other.hex`
    // overrides the MEM_INIT_FILE parameter without recompiling, so
    // one compiled simulation + one testbench can run any program.
    integer i;
    string  hexfile_plusarg;
    initial begin
        for (i = 0; i < 256; i = i + 1)
            mem[i] = 8'h00;
        if ($value$plusargs("HEXFILE=%s", hexfile_plusarg))
            $readmemh(hexfile_plusarg, mem);
        else if (MEM_INIT_FILE != "")
            $readmemh(MEM_INIT_FILE, mem);
    end

    assign rdata = mem[addr];

    always @(posedge clk) begin
        if (we)
            mem[addr] <= wdata;
    end

endmodule

8bitProcessor/control_unit.v


module control_unit (
    input  wire       clk,
    input  wire       reset,

    // status inputs from the datapath
    input  wire [7:0] ir,        // current opcode 
    input  wire       flagZ,
    input  wire       flagC,

    // ---------------- control outputs ----------------
    output reg  [3:0] state,          // current FSM state 

    // memory bus control
    output reg  [1:0] mem_addr_sel,   // 00=PC 01=OPR 10=SP 11=SP+1
    output reg         mem_we,
    output reg         mem_wdata_sel, // 0 = A, 1 = PC

    // register load/increment enables
    output reg         ir_ld,
    output reg         opr_ld,
    output reg         pc_inc,
    output reg         pc_ld,
    output reg         pc_load_sel,   // 0 = OPR, 1 = mem_rdata (stack)
    output reg         sp_inc,
    output reg         sp_dec,
    output reg         a_ld,
    output reg  [2:0]  a_sel,         // 0=alu_result 1=mem_rdata 2=OPR 3=B 4=in_port
    output reg         b_ld,
    output reg         out_ld,
    output reg         flag_z_we,
    output reg         flag_c_we,

    // ALU control
    output reg  [3:0]  alu_op,
    output reg         alu_a_sel,     // 0 = A, 1 = mem_rdata
    output reg         alu_b_sel,     // 0 = mem_rdata, 1 = OPR

    output wire        halted
);

    // ---------------- Opcodes ----------------
    localparam OP_NOP  = 8'h00;
    localparam OP_LDA  = 8'h01;
    localparam OP_STA  = 8'h02;
    localparam OP_LDI  = 8'h03;
    localparam OP_ADD  = 8'h04;
    localparam OP_ADI  = 8'h05;
    localparam OP_SUB  = 8'h06;
    localparam OP_SBI  = 8'h07;
    localparam OP_ANDA = 8'h08;
    localparam OP_ORA  = 8'h09;
    localparam OP_XORA = 8'h0A;
    localparam OP_JMP  = 8'h0B;
    localparam OP_JZ   = 8'h0C;
    localparam OP_JNZ  = 8'h0D;
    localparam OP_JC   = 8'h0E;
    localparam OP_CALL = 8'h0F;
    localparam OP_RET  = 8'h10;
    localparam OP_OUT  = 8'h11;
    localparam OP_IN   = 8'h12;
    localparam OP_MOVAB= 8'h13;
    localparam OP_MOVBA= 8'h14;
    localparam OP_INC  = 8'h15;
    localparam OP_DEC  = 8'h16;
    localparam OP_CMA  = 8'h17;
    localparam OP_SHL  = 8'h18;
    localparam OP_SHR  = 8'h19;
    localparam OP_PUSH = 8'h1A;
    localparam OP_POP  = 8'h1B;
    localparam OP_HLT  = 8'hFF;

    // ALU op codes (must match alu8.v)
    localparam ALU_ADD=4'h0, ALU_SUB=4'h1, ALU_AND=4'h2, ALU_OR=4'h3,
               ALU_XOR=4'h4, ALU_NOT=4'h5, ALU_SHL=4'h6, ALU_SHR=4'h7,
               ALU_PASS_A=4'h8, ALU_INC=4'h9, ALU_DEC=4'hA;

    // ---------------- FSM states ----------------
    localparam S_FETCH    = 4'd0;
    localparam S_DECODE   = 4'd1;
    localparam S_OPERAND  = 4'd2;
    localparam S_EXEC1    = 4'd3;
    localparam S_MEMOP    = 4'd4;
    localparam S_MEMWR    = 4'd5;
    localparam S_PUSHWR   = 4'd6;
    localparam S_STACKRD  = 4'd7;
    localparam S_CALLJUMP = 4'd8;
    localparam S_HALT     = 4'd9;

    reg [3:0] next_state;

    function is_two_byte;
        input [7:0] opc;
        begin
            case (opc)
                OP_LDA, OP_STA, OP_LDI, OP_ADD, OP_ADI, OP_SUB, OP_SBI,
                OP_ANDA, OP_ORA, OP_XORA, OP_JMP, OP_JZ, OP_JNZ, OP_JC,
                OP_CALL: is_two_byte = 1'b1;
                default: is_two_byte = 1'b0;
            endcase
        end
    endfunction

    // ================= Combinational control signal generation =================
    always @(*) begin
        // ---- safe defaults every cycle ----
        next_state    = state;
        mem_addr_sel  = 2'b00;   // PC
        mem_we        = 1'b0;
        mem_wdata_sel = 1'b0;    // A
        ir_ld         = 1'b0;
        opr_ld        = 1'b0;
        pc_inc        = 1'b0;
        pc_ld         = 1'b0;
        pc_load_sel   = 1'b0;    // OPR
        sp_inc        = 1'b0;
        sp_dec        = 1'b0;
        a_ld          = 1'b0;
        a_sel         = 3'd0;    // alu_result
        b_ld          = 1'b0;
        out_ld        = 1'b0;
        flag_z_we     = 1'b0;
        flag_c_we     = 1'b0;
        alu_op        = ALU_PASS_A;
        alu_a_sel     = 1'b0;    // A
        alu_b_sel     = 1'b0;    // mem_rdata

        case (state)
            // ---- fetch opcode byte ----
            S_FETCH: begin
                mem_addr_sel = 2'b00; // PC
                ir_ld        = 1'b1;
                pc_inc       = 1'b1;
                next_state   = S_DECODE;
            end

            // ---- route by opcode class ----
            S_DECODE: begin
                if (ir == OP_HLT)
                    next_state = S_HALT;
                else if (ir == OP_RET || ir == OP_POP)
                    next_state = S_STACKRD;
                else if (ir == OP_PUSH)
                    next_state = S_PUSHWR;
                else if (is_two_byte(ir))
                    next_state = S_OPERAND;
                else
                    next_state = S_EXEC1;
            end

            // ---- fetch operand byte ----
            S_OPERAND: begin
                mem_addr_sel = 2'b00; // PC
                opr_ld       = 1'b1;
                pc_inc       = 1'b1;
                case (ir)
                    OP_LDA, OP_ADD, OP_SUB, OP_ANDA, OP_ORA, OP_XORA:
                        next_state = S_MEMOP;
                    OP_STA:
                        next_state = S_MEMWR;
                    OP_CALL:
                        next_state = S_PUSHWR;
                    default: // LDI, ADI, SBI, JMP, JZ, JNZ, JC
                        next_state = S_EXEC1;
                endcase
            end

            // ---- ALU op using MEM[OPR] ----
            S_MEMOP: begin
                mem_addr_sel = 2'b01; // OPR
                a_ld         = 1'b1;
                a_sel        = 3'd0;  // alu_result
                flag_z_we    = 1'b1;
                case (ir)
                    OP_LDA:  begin alu_a_sel = 1'b1; alu_op = ALU_PASS_A; end            // alu_a = mem_rdata
                    OP_ADD:  begin alu_a_sel = 1'b0; alu_b_sel = 1'b0; alu_op = ALU_ADD; flag_c_we = 1'b1; end
                    OP_SUB:  begin alu_a_sel = 1'b0; alu_b_sel = 1'b0; alu_op = ALU_SUB; flag_c_we = 1'b1; end
                    OP_ANDA: begin alu_a_sel = 1'b0; alu_b_sel = 1'b0; alu_op = ALU_AND; end
                    OP_ORA:  begin alu_a_sel = 1'b0; alu_b_sel = 1'b0; alu_op = ALU_OR;  end
                    OP_XORA: begin alu_a_sel = 1'b0; alu_b_sel = 1'b0; alu_op = ALU_XOR; end
                    default: ;
                endcase
                next_state = S_FETCH;
            end

            // ---- STA: MEM[OPR] <- A ----
            S_MEMWR: begin
                mem_addr_sel  = 2'b01; // OPR
                mem_we        = 1'b1;
                mem_wdata_sel = 1'b0;  // A
                next_state    = S_FETCH;
            end

            // ---- PUSH data(A) or CALL push(PC) at MEM[SP] ----
            S_PUSHWR: begin
                mem_addr_sel  = 2'b10; // SP
                mem_we        = 1'b1;
                mem_wdata_sel = (ir == OP_CALL) ? 1'b1 : 1'b0; // PC : A
                sp_dec        = 1'b1;
                next_state    = (ir == OP_CALL) ? S_CALLJUMP : S_FETCH;
            end

            // ---- POP / RET : read MEM[SP+1] ----
            S_STACKRD: begin
                mem_addr_sel = 2'b11; // SP+1
                sp_inc       = 1'b1;
                if (ir == OP_POP) begin
                    a_ld  = 1'b1;
                    a_sel = 3'd1; // mem_rdata
                end else if (ir == OP_RET) begin
                    pc_ld       = 1'b1;
                    pc_load_sel = 1'b1; // mem_rdata
                end
                next_state = S_FETCH;
            end

            // ---- second half of CALL: PC <- OPR ----
            S_CALLJUMP: begin
                pc_ld       = 1'b1;
                pc_load_sel = 1'b0; // OPR
                next_state  = S_FETCH;
            end

            // ---- single-cycle execute (immediates / reg-only / jumps) ----
            S_EXEC1: begin
                case (ir)
                    OP_NOP: ;
                    OP_LDI: begin a_ld = 1'b1; a_sel = 3'd2; end // OPR
                    OP_ADI: begin
                        alu_a_sel = 1'b0; alu_b_sel = 1'b1; alu_op = ALU_ADD; // A + OPR
                        a_ld = 1'b1; a_sel = 3'd0; flag_z_we = 1'b1; flag_c_we = 1'b1;
                    end
                    OP_SBI: begin
                        alu_a_sel = 1'b0; alu_b_sel = 1'b1; alu_op = ALU_SUB; // A - OPR
                        a_ld = 1'b1; a_sel = 3'd0; flag_z_we = 1'b1; flag_c_we = 1'b1;
                    end
                    OP_JMP: begin pc_ld = 1'b1; pc_load_sel = 1'b0; end
                    OP_JZ:  begin pc_ld = flagZ;  pc_load_sel = 1'b0; end
                    OP_JNZ: begin pc_ld = !flagZ; pc_load_sel = 1'b0; end
                    OP_JC:  begin pc_ld = flagC;  pc_load_sel = 1'b0; end
                    OP_OUT: out_ld = 1'b1;
                    OP_IN:  begin a_ld = 1'b1; a_sel = 3'd4; end // in_port
                    OP_MOVAB: b_ld = 1'b1;
                    OP_MOVBA: begin a_ld = 1'b1; a_sel = 3'd3; end // B
                    OP_INC: begin
                        alu_a_sel = 1'b0; alu_op = ALU_INC;
                        a_ld = 1'b1; a_sel = 3'd0; flag_z_we = 1'b1; flag_c_we = 1'b1;
                    end
                    OP_DEC: begin
                        alu_a_sel = 1'b0; alu_op = ALU_DEC;
                        a_ld = 1'b1; a_sel = 3'd0; flag_z_we = 1'b1; flag_c_we = 1'b1;
                    end
                    OP_CMA: begin
                        alu_a_sel = 1'b0; alu_op = ALU_NOT;
                        a_ld = 1'b1; a_sel = 3'd0; // no flag update, matches classic CMA behavior
                    end
                    OP_SHL: begin
                        alu_a_sel = 1'b0; alu_op = ALU_SHL;
                        a_ld = 1'b1; a_sel = 3'd0; flag_z_we = 1'b1; flag_c_we = 1'b1;
                    end
                    OP_SHR: begin
                        alu_a_sel = 1'b0; alu_op = ALU_SHR;
                        a_ld = 1'b1; a_sel = 3'd0; flag_z_we = 1'b1; flag_c_we = 1'b1;
                    end
                    default: ;
                endcase
                next_state = S_FETCH;
            end

            S_HALT: next_state = S_HALT;

            default: next_state = S_FETCH;
        endcase
    end

    // ================= Sequential: state register only =================
    always @(posedge clk) begin
        if (reset)
            state <= S_FETCH;
        else
            state <= next_state;
    end

    assign halted = (state == S_HALT);

endmodule

8bitProcessor/cpu8.v
module cpu8 #(
    parameter MEM_INIT_FILE = ""
) (
    input  wire       clk,
    input  wire       reset,
    input  wire [7:0] in_port,
    output reg  [7:0] out_port,
    output wire       halted,
    // debug/observation
    output wire [7:0] dbg_pc,
    output wire [7:0] dbg_a,
    output wire [7:0] dbg_b,
    output wire [7:0] dbg_sp,
    output wire [7:0] dbg_ir,
    output wire [3:0] dbg_state,
    output wire       dbg_zero,
    output wire       dbg_carry
);

    // ---------------- Architectural registers ----------------
    reg [7:0] PC, SP, A, B, IR, OPR;
    reg       flagZ, flagC;

    // ---------------- Control <-> Datapath wires ----------------
    wire [1:0] mem_addr_sel;
    wire       mem_we;
    wire       mem_wdata_sel;
    wire       ir_ld, opr_ld;
    wire       pc_inc, pc_ld, pc_load_sel;
    wire       sp_inc, sp_dec;
    wire       a_ld;
    wire [2:0] a_sel;
    wire       b_ld;
    wire       out_ld;
    wire       flag_z_we, flag_c_we;
    wire [3:0] alu_op;
    wire       alu_a_sel, alu_b_sel;
    wire [3:0] cu_state;

    control_unit u_ctrl (
        .clk           (clk),
        .reset         (reset),
        .ir            (IR),
        .flagZ         (flagZ),
        .flagC         (flagC),
        .state         (cu_state),
        .mem_addr_sel  (mem_addr_sel),
        .mem_we        (mem_we),
        .mem_wdata_sel (mem_wdata_sel),
        .ir_ld         (ir_ld),
        .opr_ld        (opr_ld),
        .pc_inc        (pc_inc),
        .pc_ld         (pc_ld),
        .pc_load_sel   (pc_load_sel),
        .sp_inc        (sp_inc),
        .sp_dec        (sp_dec),
        .a_ld          (a_ld),
        .a_sel         (a_sel),
        .b_ld          (b_ld),
        .out_ld        (out_ld),
        .flag_z_we     (flag_z_we),
        .flag_c_we     (flag_c_we),
        .alu_op        (alu_op),
        .alu_a_sel     (alu_a_sel),
        .alu_b_sel     (alu_b_sel),
        .halted        (halted)
    );

    // ---------------- Memory bus mux ----------------
    reg  [7:0] mem_addr;
    wire [7:0] mem_wdata;
    wire [7:0] mem_rdata;

    always @(*) begin
        case (mem_addr_sel)
            2'b00: mem_addr = PC;
            2'b01: mem_addr = OPR;
            2'b10: mem_addr = SP;
            2'b11: mem_addr = SP + 8'd1;
            default: mem_addr = PC;
        endcase
    end

    assign mem_wdata = mem_wdata_sel ? PC : A;

    memory8 #(.MEM_INIT_FILE(MEM_INIT_FILE)) u_mem (
        .clk   (clk),
        .addr  (mem_addr),
        .wdata (mem_wdata),
        .we    (mem_we),
        .rdata (mem_rdata)
    );

    // ---------------- ALU + input muxes ----------------
    wire [7:0] alu_a = alu_a_sel ? mem_rdata : A;
    wire [7:0] alu_b = alu_b_sel ? OPR       : mem_rdata;
    wire [7:0] alu_result;
    wire       alu_zero, alu_carry;

    alu8 u_alu (
        .a      (alu_a),
        .b      (alu_b),
        .op     (alu_op),
        .result (alu_result),
        .zero   (alu_zero),
        .carry  (alu_carry)
    );

    // ---------------- A-register write-back mux ----------------
    reg [7:0] a_next;
    always @(*) begin
        case (a_sel)
            3'd0: a_next = alu_result;
            3'd1: a_next = mem_rdata;
            3'd2: a_next = OPR;
            3'd3: a_next = B;
            3'd4: a_next = in_port;
            default: a_next = alu_result;
        endcase
    end

    // ---------------- PC write-back mux ----------------
    wire [7:0] pc_next = pc_load_sel ? mem_rdata : OPR;

    // ================= Sequential register updates =================
    always @(posedge clk) begin
        if (reset) begin
            PC       <= 8'h00;
            SP       <= 8'hFF;
            A        <= 8'h00;
            B        <= 8'h00;
            IR       <= 8'h00;
            OPR      <= 8'h00;
            flagZ    <= 1'b0;
            flagC    <= 1'b0;
            out_port <= 8'h00;
        end else begin
            if (ir_ld)  IR  <= mem_rdata;
            if (opr_ld) OPR <= mem_rdata;

            if (pc_inc)      PC <= PC + 8'd1;
            else if (pc_ld)  PC <= pc_next;

            if (sp_dec)      SP <= SP - 8'd1;
            else if (sp_inc) SP <= SP + 8'd1;

            if (a_ld) A <= a_next;
            if (b_ld) B <= A;

            if (out_ld) out_port <= A;

            if (flag_z_we) flagZ <= alu_zero;
            if (flag_c_we) flagC <= alu_carry;
        end
    end

    assign dbg_pc    = PC;
    assign dbg_a     = A;
    assign dbg_b     = B;
    assign dbg_sp    = SP;
    assign dbg_ir    = IR;
    assign dbg_state = cu_state;
    assign dbg_zero  = flagZ;
    assign dbg_carry = flagC;

endmodule

8bitProcessor/tb_cpu8.v

module tb_cpu8;

    reg clk;
    reg reset;
    reg  [7:0] in_port;
    wire [7:0] out_port;
    wire       halted;
    wire [7:0] dbg_pc, dbg_a, dbg_b, dbg_sp, dbg_ir;
    wire [3:0] dbg_state;
    wire       dbg_zero, dbg_carry;


    cpu8 dut (
        .clk      (clk),
        .reset    (reset),
        .in_port  (in_port),
        .out_port (out_port),
        .halted   (halted),
        .dbg_pc   (dbg_pc),
        .dbg_a    (dbg_a),
        .dbg_b    (dbg_b),
        .dbg_sp   (dbg_sp),
        .dbg_ir   (dbg_ir),
        .dbg_state(dbg_state),
        .dbg_zero (dbg_zero),
        .dbg_carry(dbg_carry)
    );

    initial clk = 0;
    always #5 clk = ~clk;

    string  hexfile;
    string  testname;
    integer expected;
    integer have_expected;
    integer max_cycles;
    integer cycle_count;

    initial begin
        if (!$value$plusargs("HEXFILE=%s", hexfile))
            hexfile = "sw/program.hex";
        if (!$value$plusargs("TESTNAME=%s", testname))
            testname = "unnamed_test";
        if (!$value$plusargs("MAXCYCLES=%d", max_cycles))
            max_cycles = 2000;
        have_expected = $value$plusargs("EXPECTED=%d", expected);

        $dumpfile({"cpu8_", testname, ".vcd"});
        $dumpvars(0, tb_cpu8);

        $display("====================================================");
        $display("TEST: %s", testname);
        $display("HEXFILE: %s", hexfile);
        $display("====================================================");

        reset       = 1;
        in_port     = 8'h00;
        cycle_count = 0;
        repeat (2) @(posedge clk);
        reset = 0;

        while (!halted && cycle_count < max_cycles) begin
            @(posedge clk);
            cycle_count = cycle_count + 1;
        end

        if (halted) begin
            $display("CPU halted after %0d clock cycles", cycle_count);
            $display("Final A   = %0d (0x%02h)", dbg_a, dbg_a);
            $display("Final B   = %0d (0x%02h)", dbg_b, dbg_b);
            $display("Final PC  = 0x%02h", dbg_pc);
            $display("Final SP  = 0x%02h", dbg_sp);
            $display("OUT_PORT  = %0d (0x%02h)", out_port, out_port);
            $display("Flags     = Z:%0b C:%0b", dbg_zero, dbg_carry);
            if (have_expected) begin
                if (out_port == expected[7:0])
                    $display("RESULT: PASS (%s) -- out_port == %0d as expected", testname, expected);
                else
                    $display("RESULT: FAIL (%s) -- expected %0d, got %0d", testname, expected, out_port);
            end else begin
                $display("RESULT: DONE (%s) -- no +EXPECTED given, reporting only", testname);
            end
        end else begin
            $display("RESULT: TIMEOUT (%s) -- CPU never halted after %0d cycles", testname, cycle_count);
        end
        $display("====================================================");

        $finish;
    end

    // Cycle-by-cycle trace (visible with $display, also captured in VCD)
    initial begin
        $monitor("t=%0t state=%0d PC=0x%02h IR=0x%02h A=0x%02h B=0x%02h SP=0x%02h Z=%b C=%b OUT=0x%02h",
                 $time, dbg_state, dbg_pc, dbg_ir, dbg_a, dbg_b, dbg_sp, dbg_zero, dbg_carry, out_port);
    end

endmodule

8bitProcessor/cpu8_unnamed_test.vcd
$date
	Fri Jul  3 09:22:03 2026
$end
$version
	Icarus Verilog
$end
$timescale
	1ps
$end
$scope module tb_cpu8 $end
$var wire 8 ! out_port [7:0] $end
$var wire 1 " halted $end
$var wire 1 # dbg_zero $end
$var wire 4 $ dbg_state [3:0] $end
$var wire 8 % dbg_sp [7:0] $end
$var wire 8 & dbg_pc [7:0] $end
$var wire 8 ' dbg_ir [7:0] $end
$var wire 1 ( dbg_carry $end
$var wire 8 ) dbg_b [7:0] $end
$var wire 8 * dbg_a [7:0] $end
$var reg 1 + clk $end
$var reg 8 , in_port [7:0] $end
$var reg 1 - reset $end
$var integer 32 . cycle_count [31:0] $end
$var integer 32 / expected [31:0] $end
$var integer 32 0 have_expected [31:0] $end
$var integer 32 1 max_cycles [31:0] $end
$scope module dut $end
$var wire 1 + clk $end
$var wire 8 2 dbg_a [7:0] $end
$var wire 8 3 dbg_b [7:0] $end
$var wire 1 ( dbg_carry $end
$var wire 8 4 dbg_ir [7:0] $end
$var wire 8 5 dbg_pc [7:0] $end
$var wire 8 6 dbg_sp [7:0] $end
$var wire 4 7 dbg_state [3:0] $end
$var wire 1 # dbg_zero $end
$var wire 8 8 in_port [7:0] $end
$var wire 1 - reset $end
$var wire 1 9 sp_inc $end
$var wire 1 : sp_dec $end
$var wire 8 ; pc_next [7:0] $end
$var wire 1 < pc_load_sel $end
$var wire 1 = pc_ld $end
$var wire 1 > pc_inc $end
$var wire 1 ? out_ld $end
$var wire 1 @ opr_ld $end
$var wire 1 A mem_we $end
$var wire 1 B mem_wdata_sel $end
$var wire 8 C mem_wdata [7:0] $end
$var wire 8 D mem_rdata [7:0] $end
$var wire 2 E mem_addr_sel [1:0] $end
$var wire 1 F ir_ld $end
$var wire 1 " halted $end
$var wire 1 G flag_z_we $end
$var wire 1 H flag_c_we $end
$var wire 4 I cu_state [3:0] $end
$var wire 1 J b_ld $end
$var wire 1 K alu_zero $end
$var wire 8 L alu_result [7:0] $end
$var wire 4 M alu_op [3:0] $end
$var wire 1 N alu_carry $end
$var wire 1 O alu_b_sel $end
$var wire 8 P alu_b [7:0] $end
$var wire 1 Q alu_a_sel $end
$var wire 8 R alu_a [7:0] $end
$var wire 3 S a_sel [2:0] $end
$var wire 1 T a_ld $end
$var parameter 0 U MEM_INIT_FILE $end
$var reg 8 V A [7:0] $end
$var reg 8 W B [7:0] $end
$var reg 8 X IR [7:0] $end
$var reg 8 Y OPR [7:0] $end
$var reg 8 Z PC [7:0] $end
$var reg 8 [ SP [7:0] $end
$var reg 8 \ a_next [7:0] $end
$var reg 1 ] flagC $end
$var reg 1 ^ flagZ $end
$var reg 8 _ mem_addr [7:0] $end
$var reg 8 ` out_port [7:0] $end
$scope module u_alu $end
$var wire 8 a a [7:0] $end
$var wire 8 b b [7:0] $end
$var wire 1 K zero $end
$var wire 4 c op [3:0] $end
$var parameter 4 d ALU_ADD $end
$var parameter 4 e ALU_AND $end
$var parameter 4 f ALU_DEC $end
$var parameter 4 g ALU_INC $end
$var parameter 4 h ALU_NOT $end
$var parameter 4 i ALU_OR $end
$var parameter 4 j ALU_PASS_A $end
$var parameter 4 k ALU_SHL $end
$var parameter 4 l ALU_SHR $end
$var parameter 4 m ALU_SUB $end
$var parameter 4 n ALU_XOR $end
$var reg 1 N carry $end
$var reg 8 o result [7:0] $end
$var reg 9 p wide [8:0] $end
$upscope $end
$scope module u_ctrl $end
$var wire 1 + clk $end
$var wire 1 ] flagC $end
$var wire 1 ^ flagZ $end
$var wire 8 q ir [7:0] $end
$var wire 1 - reset $end
$var wire 1 " halted $end
$var parameter 4 r ALU_ADD $end
$var parameter 4 s ALU_AND $end
$var parameter 4 t ALU_DEC $end
$var parameter 4 u ALU_INC $end
$var parameter 4 v ALU_NOT $end
$var parameter 4 w ALU_OR $end
$var parameter 4 x ALU_PASS_A $end
$var parameter 4 y ALU_SHL $end
$var parameter 4 z ALU_SHR $end
$var parameter 4 { ALU_SUB $end
$var parameter 4 | ALU_XOR $end
$var parameter 8 } OP_ADD $end
$var parameter 8 ~ OP_ADI $end
$var parameter 8 !" OP_ANDA $end
$var parameter 8 "" OP_CALL $end
$var parameter 8 #" OP_CMA $end
$var parameter 8 $" OP_DEC $end
$var parameter 8 %" OP_HLT $end
$var parameter 8 &" OP_IN $end
$var parameter 8 '" OP_INC $end
$var parameter 8 (" OP_JC $end
$var parameter 8 )" OP_JMP $end
$var parameter 8 *" OP_JNZ $end
$var parameter 8 +" OP_JZ $end
$var parameter 8 ," OP_LDA $end
$var parameter 8 -" OP_LDI $end
$var parameter 8 ." OP_MOVAB $end
$var parameter 8 /" OP_MOVBA $end
$var parameter 8 0" OP_NOP $end
$var parameter 8 1" OP_ORA $end
$var parameter 8 2" OP_OUT $end
$var parameter 8 3" OP_POP $end
$var parameter 8 4" OP_PUSH $end
$var parameter 8 5" OP_RET $end
$var parameter 8 6" OP_SBI $end
$var parameter 8 7" OP_SHL $end
$var parameter 8 8" OP_SHR $end
$var parameter 8 9" OP_STA $end
$var parameter 8 :" OP_SUB $end
$var parameter 8 ;" OP_XORA $end
$var parameter 4 <" S_CALLJUMP $end
$var parameter 4 =" S_DECODE $end
$var parameter 4 >" S_EXEC1 $end
$var parameter 4 ?" S_FETCH $end
$var parameter 4 @" S_HALT $end
$var parameter 4 A" S_MEMOP $end
$var parameter 4 B" S_MEMWR $end
$var parameter 4 C" S_OPERAND $end
$var parameter 4 D" S_PUSHWR $end
$var parameter 4 E" S_STACKRD $end
$var reg 1 T a_ld $end
$var reg 3 F" a_sel [2:0] $end
$var reg 1 Q alu_a_sel $end
$var reg 1 O alu_b_sel $end
$var reg 4 G" alu_op [3:0] $end
$var reg 1 J b_ld $end
$var reg 1 H flag_c_we $end
$var reg 1 G flag_z_we $end
$var reg 1 F ir_ld $end
$var reg 2 H" mem_addr_sel [1:0] $end
$var reg 1 B mem_wdata_sel $end
$var reg 1 A mem_we $end
$var reg 4 I" next_state [3:0] $end
$var reg 1 @ opr_ld $end
$var reg 1 ? out_ld $end
$var reg 1 > pc_inc $end
$var reg 1 = pc_ld $end
$var reg 1 < pc_load_sel $end
$var reg 1 : sp_dec $end
$var reg 1 9 sp_inc $end
$var reg 4 J" state [3:0] $end
$scope function is_two_byte $end
$var reg 8 K" opc [7:0] $end
$upscope $end
$upscope $end
$scope module u_mem $end
$var wire 8 L" addr [7:0] $end
$var wire 1 + clk $end
$var wire 8 M" rdata [7:0] $end
$var wire 8 N" wdata [7:0] $end
$var wire 1 A we $end
$var parameter 0 O" MEM_INIT_FILE $end
$var integer 32 P" i [31:0] $end
$upscope $end
$upscope $end
$upscope $end
$enddefinitions $end
$comment Show the parameter values. $end
$dumpall
b O"
b111 E"
b110 D"
b10 C"
b101 B"
b100 A"
b1001 @"
b0 ?"
b11 >"
b1 ="
b1000 <"
b1010 ;"
b110 :"
b10 9"
b11001 8"
b11000 7"
b111 6"
b10000 5"
b11010 4"
b11011 3"
b10001 2"
b1001 1"
b0 0"
b10100 /"
b10011 ."
b11 -"
b1 ,"
b1100 +"
b1101 *"
b1011 )"
b1110 ("
b10101 '"
b10010 &"
b11111111 %"
b10110 $"
b10111 #"
b1111 ""
b1000 !"
b101 ~
b100 }
b100 |
b1 {
b111 z
b110 y
b1000 x
b11 w
b101 v
b1001 u
b1010 t
b10 s
b0 r
b100 n
b1 m
b111 l
b110 k
b1000 j
b11 i
b101 h
b1001 g
b1010 f
b10 e
b0 d
b U
$end
#0
$dumpvars
b100000000 P"
bx N"
bx M"
bx L"
bx K"
bx J"
bx I"
bx H"
bx G"
bx F"
bx q
bx p
bx o
bx c
bx b
bx a
bx `
bx _
x^
x]
bx \
bx [
bx Z
bx Y
bx X
bx W
bx V
xT
bx S
bx R
xQ
bx P
xO
xN
bx M
bx L
xK
xJ
bx I
xH
xG
xF
bx E
bx D
bx C
xB
xA
x@
x?
x>
x=
x<
bx ;
x:
x9
b0 8
bx 7
bx 6
bx 5
bx 4
bx 3
bx 2
b11111010000 1
b0 0
bx /
b0 .
1-
b0 ,
0+
bx *
bx )
x(
bx '
bx &
bx %
bx $
x#
x"
bx !
$end
#5000
b0 \
1K
b0 L
b0 o
0N
b0 p
b0 P
b0 b
b0 ;
0O
0Q
b1000 M
b1000 c
b1000 G"
0H
0G
0?
0J
b0 S
b0 F"
0T
0:
09
0<
0=
1>
0@
1F
0B
0A
b0 E
b0 H"
b1 I"
b0 R
b0 a
b0 D
b0 M"
b0 _
b0 L"
b0 C
b0 N"
0"
b0 $
b0 7
b0 I
b0 J"
b0 !
b0 `
0(
0]
0#
0^
b0 Y
b0 '
b0 4
b0 X
b0 q
b0 )
b0 3
b0 W
b0 *
b0 2
b0 V
b11111111 %
b11111111 6
b11111111 [
b0 &
b0 5
b0 Z
1+
#10000
0+
#15000
0-
1+
#20000
0+
#25000
b11 I"
b0 K"
0>
0F
b1 _
b1 L"
b1 $
b1 7
b1 I
b1 J"
b1 &
b1 5
b1 Z
b1 .
1+
#30000
0+
#35000
b0 I"
b11 $
b11 7
b11 I
b11 J"
b10 .
1+
#40000
0+
#45000
b1 I"
1>
1F
b0 $
b0 7
b0 I
b0 J"
b11 .
1+
#50000
0+
#55000
b10 _
b10 L"
b11 I"
0>
0F
b10 &
b10 5
b10 Z
b1 $
b1 7
b1 I
b1 J"
b100 .
1+
#60000
0+
#65000
b0 I"
b11 $
b11 7
b11 I
b11 J"
b101 .
1+
#70000
0+
#75000
b1 I"
1>
1F
b0 $
b0 7
b0 I
b0 J"
b110 .
1+
#80000
0+
#85000
b11 I"
0>
0F
b11 _
b11 L"
b1 $
b1 7
b1 I
b1 J"
b11 &
b11 5
b11 Z
b111 .
1+
#90000
0+
